lipsum/__init__.py
lipsumAPI-1.1.dist-info/METADATA
lipsumAPI-1.1.dist-info/RECORD
lipsumAPI-1.1.dist-info/WHEEL
lipsumAPI-1.1.dist-info/top_level.txt
