Metadata-Version: 2.1
Name: lipsumAPI
Version: 1.1
Summary: A lipsum.com API for Python.
Home-page: https://gitlab.com/xedre/Python-Lipsum-API
Author: Theo Toth
Author-email: lipsumapi@xed.re
License: UNKNOWN
Platform: UNKNOWN
Classifier: Programming Language :: Python :: 3
Classifier: License :: OSI Approved :: MIT License
Classifier: Operating System :: OS Independent
Classifier: Natural Language :: English
Classifier: Topic :: Internet
Classifier: Topic :: Utilities
